{
  "question_id": "samplenew3_00000195",
  "chinese_text": "感动朕的人朕绝不轻饶",
  "emotion_statistics": {
    "total_runs": 10,
    "total_emotion_instances": 35,
    "unique_emotions": 15,
    "emotion_details": {
      "Moved": {
        "count": 9,
        "frequency": 0.9,
        "percentage": 90.0
      },
      "Determined": {
        "count": 5,
        "frequency": 0.5,
        "percentage": 50.0
      },
      "Grateful": {
        "count": 4,
        "frequency": 0.4,
        "percentage": 40.0
      },
      "Touched": {
        "count": 3,
        "frequency": 0.3,
        "percentage": 30.0
      },
      "Determination": {
        "count": 2,
        "frequency": 0.2,
        "percentage": 20.0
      },
      "Gratitude": {
        "count": 2,
        "frequency": 0.2,
        "percentage": 20.0
      },
      "Nostalgic": {
        "count": 2,
        "frequency": 0.2,
        "percentage": 20.0
      },
      "Indignation": {
        "count": 1,
        "frequency": 0.1,
        "percentage": 10.0
      },
      "Proud": {
        "count": 1,
        "frequency": 0.1,
        "percentage": 10.0
      },
      "Indignant": {
        "count": 1,
        "frequency": 0.1,
        "percentage": 10.0
      },
      "Loyalty": {
        "count": 1,
        "frequency": 0.1,
        "percentage": 10.0
      },
      "Devotion": {
        "count": 1,
        "frequency": 0.1,
        "percentage": 10.0
      },
      "Inspiration": {
        "count": 1,
        "frequency": 0.1,
        "percentage": 10.0
      },
      "Respectful": {
        "count": 1,
        "frequency": 0.1,
        "percentage": 10.0
      },
      "Humble": {
        "count": 1,
        "frequency": 0.1,
        "percentage": 10.0
      }
    }
  },
  "summary": {
    "most_frequent_emotion": [
      "Moved",
      {
        "count": 9,
        "frequency": 0.9,
        "percentage": 90.0
      }
    ],
    "top_3_emotions": [
      "Moved",
      "Determined",
      "Grateful"
    ]
  },
  "model_used": "meta-llama/Meta-Llama-3-8B-Instruct",
  "timestamp": "2025-07-14T22:42:19.852598"
}